microbeseq_nbdev_example/__init__.py
microbeseq_nbdev_example/_modidx.py
microbeseq_nbdev_example/core.py
microbeseq_nbdev_example/hello_world.py
microbeseq_nbdev_example/config/config.default.env
microbeseq_nbdev_example/config/config.default.yaml
microbeseq_nbdev_example-0.0.5.dist-info/LICENSE
microbeseq_nbdev_example-0.0.5.dist-info/METADATA
microbeseq_nbdev_example-0.0.5.dist-info/WHEEL
microbeseq_nbdev_example-0.0.5.dist-info/entry_points.txt
microbeseq_nbdev_example-0.0.5.dist-info/top_level.txt
microbeseq_nbdev_example-0.0.5.dist-info/RECORD
