Metadata-Version: 2.1
Name: microbeseq_nbdev_example
Version: 0.0.5
Summary: TODO
Home-page: https://github.com/$GIT_USER_NAME/microbeseq_nbdev_example
Author: $GIT_USER_NAME
Author-email: kimleeng@gmail.com
License: MIT License
Keywords: nbdev jupyter notebook python
Classifier: Development Status :: 4 - Beta
Classifier: Intended Audience :: Developers
Classifier: Natural Language :: English
Classifier: Programming Language :: Python :: 3.7
Classifier: Programming Language :: Python :: 3.8
Classifier: Programming Language :: Python :: 3.9
Classifier: Programming Language :: Python :: 3.10
Classifier: License :: OSI Approved :: MIT License
Requires-Python: >=3.7
License-File: LICENSE
Requires-Dist: fastcore
Requires-Dist: python-dotenv
Requires-Dist: envyaml
Requires-Dist: pandas
Provides-Extra: dev
